wfchecker/__init__.py
wfchecker/utils.py
wfchecker/wf_checker.py
wfchecker-0.1.dist-info/DESCRIPTION.rst
wfchecker-0.1.dist-info/METADATA
wfchecker-0.1.dist-info/RECORD
wfchecker-0.1.dist-info/WHEEL
wfchecker-0.1.dist-info/entry_points.txt
wfchecker-0.1.dist-info/metadata.json
wfchecker-0.1.dist-info/top_level.txt
