Metadata-Version: 2.0
Name: wfchecker
Version: 0.1
Summary: Extracts javascript code from a json file and checks it for syntax errors.
Home-page: https://bitbucket.org/longedok/wf_checker
Author: Evgeniy Kartavkyh
Author-email: longedok@gmail.com
License: MIT
Platform: UNKNOWN
